{
  "name": "小学最常用20首古诗",
  "category": "古诗",
  "items": [
    {
      "title": "静夜思",
      "author": "李白",
      "content": "床前明月光，疑是地上霜。举头望明月，低头思故乡。"
    },
    {
      "title": "春晓",
      "author": "孟浩然",
      "content": "春眠不觉晓，处处闻啼鸟。夜来风雨声，花落知多少。"
    },
    {
      "title": "悯农",
      "author": "李绅",
      "content": "锄禾日当午，汗滴禾下土。谁知盘中餐，粒粒皆辛苦。"
    },
    {
      "title": "咏鹅",
      "author": "骆宾王",
      "content": "鹅鹅鹅，曲项向天歌。白毛浮绿水，红掌拨清波。"
    },
    {
      "title": "江南",
      "author": "汉乐府",
      "content": "江南可采莲，莲叶何田田。鱼戏莲叶间，鱼戏莲叶东，鱼戏莲叶西，鱼戏莲叶南，鱼戏莲叶北。"
    },
    {
      "title": "画",
      "author": "王维",
      "content": "远看山有色，近听水无声。春去花还在，人来鸟不惊。"
    },
    {
      "title": "古朗月行",
      "author": "李白",
      "content": "小时不识月，呼作白玉盘。又疑瑶台镜，飞在青云端。"
    },
    {
      "title": "风",
      "author": "李峤",
      "content": "解落三秋叶，能开二月花。过江千尺浪，入竹万竿斜。"
    },
    {
      "title": "登鹳雀楼",
      "author": "王之涣",
      "content": "白日依山尽，黄河入海流。欲穷千里目，更上一层楼。"
    },
    {
      "title": "望庐山瀑布",
      "author": "李白",
      "content": "日照香炉生紫烟，遥看瀑布挂前川。飞流直下三千尺，疑是银河落九天。"
    },
    {
      "title": "绝句",
      "author": "杜甫",
      "content": "两个黄鹂鸣翠柳，一行白鹭上青天。窗含西岭千秋雪，门泊东吴万里船。"
    },
    {
      "title": "草",
      "author": "白居易",
      "content": "离离原上草，一岁一枯荣。野火烧不尽，春风吹又生。"
    },
    {
      "title": "咏柳",
      "author": "贺知章",
      "content": "碧玉妆成一树高，万条垂下绿丝绦。不知细叶谁裁出，二月春风似剪刀。"
    },
    {
      "title": "小池",
      "author": "杨万里",
      "content": "泉眼无声惜细流，树阴照水爱晴柔。小荷才露尖尖角，早有蜻蜓立上头。"
    },
    {
      "title": "村居",
      "author": "高鼎",
      "content": "草长莺飞二月天，拂堤杨柳醉春烟。儿童散学归来早，忙趁东风放纸鸢。"
    },
    {
      "title": "山行",
      "author": "杜牧",
      "content": "远上寒山石径斜，白云生处有人家。停车坐爱枫林晚，霜叶红于二月花。"
    },
    {
      "title": "回乡偶书",
      "author": "贺知章",
      "content": "少小离家老大回，乡音无改鬓毛衰。儿童相见不相识，笑问客从何处来。"
    },
    {
      "title": "赠汪伦",
      "author": "李白",
      "content": "李白乘舟将欲行，忽闻岸上踏歌声。桃花潭水深千尺，不及汪伦送我情。"
    },
    {
      "title": "清明",
      "author": "杜牧",
      "content": "清明时节雨纷纷，路上行人欲断魂。借问酒家何处有，牧童遥指杏花村。"
    },
    {
      "title": "游子吟",
      "author": "孟郊",
      "content": "慈母手中线，游子身上衣。临行密密缝，意恐迟迟归。谁言寸草心，报得三春晖。"
    }
  ]
}